[
  {
    "imgName":"1.jpg",
    "title":"san",
    "desc":"1-san"
  },
  {
    "imgName":"2.jpg",
    "title":"tuzi",
    "desc":"2-tuzi"
  },
  {
    "imgName":"3.jpg",
    "title":"ye",
    "desc":"3-ye"
  },
  {
    "imgName":"4.jpg",
    "title":"love",
    "desc":"4-love"
  },
  {
    "imgName":"5.jpg",
    "title":"hua",
    "desc":"5-hua"
  },
  {
    "imgName":"6.jpg",
    "title":"girl",
    "desc":"6-girl"
  },
  {
    "imgName":"7.jpg",
    "title":"light",
    "desc":"7-light"
  },
  {
    "imgName":"8.jpg",
    "title":"heart",
    "desc":"8-heart"
  },
  {
    "imgName":"9.jpg",
    "title":"zz",
    "desc":"9-zz"
  }
]
